recursive_pipes/IterPipe.py
recursive_pipes/__init__.py
recursive_pipes/pipes.py
recursive_pipes-0.0.1.dist-info/METADATA
recursive_pipes-0.0.1.dist-info/WHEEL
recursive_pipes-0.0.1.dist-info/licenses/LICENSE
recursive_pipes-0.0.1.dist-info/RECORD
